nodev.specs-0.3.1-py3.5-nspkg.pth
nodev/specs/__init__.py
nodev/specs/generic.py
nodev.specs-0.3.1.dist-info/DESCRIPTION.rst
nodev.specs-0.3.1.dist-info/METADATA
nodev.specs-0.3.1.dist-info/RECORD
nodev.specs-0.3.1.dist-info/WHEEL
nodev.specs-0.3.1.dist-info/metadata.json
nodev.specs-0.3.1.dist-info/namespace_packages.txt
nodev.specs-0.3.1.dist-info/top_level.txt
nodev.specs-0.3.1.dist-info/zip-safe
