Metadata-Version: 2.0
Name: nodev.specs
Version: 0.3.1
Summary: nodev helpers to write specification tests.
Home-page: https://github.com/nodev-io/nodev.specs
Author: Alessandro Amici
Author-email: alexamici@gmail.com
License: MIT
Download-URL: https://github.com/nodev-io/nodev.specs/archive/0.3.1.tar.gz
Keywords: test-driven source code search nodev
Platform: UNKNOWN
Classifier: Development Status :: 2 - Pre-Alpha
Classifier: Intended Audience :: Developers
Classifier: Topic :: Software Development :: Testing
Classifier: Programming Language :: Python
Classifier: Programming Language :: Python :: 2
Classifier: Programming Language :: Python :: 2.7
Classifier: Programming Language :: Python :: 3
Classifier: Programming Language :: Python :: 3.3
Classifier: Programming Language :: Python :: 3.4
Classifier: Programming Language :: Python :: 3.5
Classifier: Programming Language :: Python :: Implementation :: CPython
Classifier: Programming Language :: Python :: Implementation :: PyPy
Classifier: Operating System :: OS Independent
Classifier: License :: OSI Approved :: MIT License
Requires-Dist: future
